setup.py
Flask_APIBlueprint.egg-info/PKG-INFO
Flask_APIBlueprint.egg-info/SOURCES.txt
Flask_APIBlueprint.egg-info/dependency_links.txt
Flask_APIBlueprint.egg-info/not-zip-safe
Flask_APIBlueprint.egg-info/requires.txt
Flask_APIBlueprint.egg-info/top_level.txt
flask_apiblueprint/__init__.py
flask_apiblueprint/apiblueprint.py